guacamole_keysyms/__init__.py
guacamole_keysyms-0.0.1.dist-info/LICENSE
guacamole_keysyms-0.0.1.dist-info/METADATA
guacamole_keysyms-0.0.1.dist-info/WHEEL
guacamole_keysyms-0.0.1.dist-info/top_level.txt
guacamole_keysyms-0.0.1.dist-info/RECORD
