Metadata-Version: 2.1
Name: guacamole-keysyms
Version: 0.0.1
Summary: Guacamole protocol key mappings for python
Home-page: https://ari-web.xyz/gh/guacamole_keysyms
Author: Ari Archer
Author-email: ari.web.xyz@gmail.com
Classifier: Programming Language :: Python :: 3
Classifier: License :: OSI Approved :: GNU General Public License v3 or later (GPLv3+)
Classifier: Operating System :: OS Independent
Requires-Python: >=3.8
License-File: LICENSE
